{
  "analysis_metadata": {
    "analysis_id": 3,
    "title": "人員配置×品質 相関分析",
    "subtitle": "Staffing Level × Quality Correlation Analysis",
    "total_hotels": 19,
    "hotels_with_staffing_data": 19,
    "data_period": "R8年度2月〜4月（日報データ）"
  },
  "staffing_analysis": {
    "correlations": {
      "staff_vs_score": {
        "r": -0.1215,
        "r_squared": 0.0148,
        "n": 17
      },
      "maids_vs_score": {
        "r": -0.0255,
        "r_squared": 0.0007,
        "n": 19
      },
      "checkers_vs_score": {
        "r": -0.1087,
        "r_squared": 0.0118,
        "n": 17
      },
      "ratio_vs_score": {
        "r": -0.3574,
        "r_squared": 0.1278,
        "n": 17
      },
      "staff_vs_claims": {
        "r": 0.1717,
        "n": 19
      }
    },
    "staffing_tiers": {
      "low_staff": {
        "count": 9,
        "avg_maids": 7.1,
        "avg_score": 8.51,
        "avg_claim_rate": 5.92
      },
      "high_staff": {
        "count": 10,
        "avg_maids": 12.6,
        "avg_score": 8.16,
        "avg_claim_rate": 6.94
      }
    },
    "optimal_staffing": {
      "top5_hotels": [
        {
          "name": "第一イン池袋",
          "avg_maids": 5.7,
          "avg_checkers": 3.6,
          "ratio": 1.6,
          "score": 9.47
        },
        {
          "name": "京成リッチモンドホテル東京錦糸町",
          "avg_maids": 8.3,
          "avg_checkers": 2.7,
          "ratio": 3.0,
          "score": 9.24
        },
        {
          "name": "コンフォートスイーツ東京ベイ",
          "avg_maids": 23.5,
          "avg_checkers": 5.9,
          "ratio": 4.0,
          "score": 9.05
        },
        {
          "name": "ホテルケヤキゲート東京府中",
          "avg_maids": 10.3,
          "avg_checkers": 1.5,
          "ratio": 7.1,
          "score": 8.95
        },
        {
          "name": "ホテルコメント横浜関内",
          "avg_maids": 9.4,
          "avg_checkers": 2.1,
          "ratio": 4.4,
          "score": 8.82
        }
      ],
      "bottom5_hotels": [
        {
          "name": "チサンホテル浜松町",
          "avg_maids": 9.2,
          "avg_checkers": null,
          "ratio": null,
          "score": 6.52
        },
        {
          "name": "コートホテル新横浜",
          "avg_maids": 8.0,
          "avg_checkers": 2.6,
          "ratio": 3.1,
          "score": 7.12
        },
        {
          "name": "アパホテル蒲田駅東",
          "avg_maids": 12.9,
          "avg_checkers": 1.0,
          "ratio": 12.9,
          "score": 7.5
        },
        {
          "name": "コンフォートホテル横浜関内",
          "avg_maids": 10.7,
          "avg_checkers": 1.0,
          "ratio": 10.7,
          "score": 7.57
        },
        {
          "name": "コンフォートホテル博多",
          "avg_maids": 17.1,
          "avg_checkers": 5.2,
          "ratio": 3.3,
          "score": 7.83
        }
      ],
      "top5_avg_ratio": 4.0,
      "bottom5_avg_ratio": 7.5
    },
    "data_points": [
      {
        "hotel_key": "daiwa_osaki",
        "name": "ダイワロイネットホテル東京大崎",
        "avg_maids": 8.6,
        "avg_checkers": 2.6,
        "avg_total_staff": 11.2,
        "maid_checker_ratio": 3.3,
        "score": 8.59,
        "cleaning_issue_rate": 8.1,
        "claim_rate": 11.83,
        "maid_data_points": 59
      },
      {
        "hotel_key": "chisan",
        "name": "チサンホテル浜松町",
        "avg_maids": 9.2,
        "avg_checkers": null,
        "avg_total_staff": null,
        "maid_checker_ratio": null,
        "score": 6.52,
        "cleaning_issue_rate": 9.3,
        "claim_rate": 0.53,
        "maid_data_points": 44
      },
      {
        "hotel_key": "hearton",
        "name": "ハートンホテル東品川",
        "avg_maids": 12.3,
        "avg_checkers": 1.5,
        "avg_total_staff": 13.8,
        "maid_checker_ratio": 8.1,
        "score": 8.43,
        "cleaning_issue_rate": 4.4,
        "claim_rate": 7.27,
        "maid_data_points": 72
      },
      {
        "hotel_key": "keyakigate",
        "name": "ホテルケヤキゲート東京府中",
        "avg_maids": 10.3,
        "avg_checkers": 1.5,
        "avg_total_staff": 11.8,
        "maid_checker_ratio": 7.1,
        "score": 8.95,
        "cleaning_issue_rate": 3.4,
        "claim_rate": 3.83,
        "maid_data_points": 72
      },
      {
        "hotel_key": "richmond_mejiro",
        "name": "リッチモンドホテル東京目白",
        "avg_maids": 6.0,
        "avg_checkers": 3.0,
        "avg_total_staff": 9.0,
        "maid_checker_ratio": 2.0,
        "score": 8.49,
        "cleaning_issue_rate": 4.1,
        "claim_rate": 0,
        "maid_data_points": 57
      },
      {
        "hotel_key": "keisei_richmond",
        "name": "京成リッチモンドホテル東京錦糸町",
        "avg_maids": 8.3,
        "avg_checkers": 2.7,
        "avg_total_staff": 11.0,
        "maid_checker_ratio": 3.0,
        "score": 9.24,
        "cleaning_issue_rate": 1.5,
        "claim_rate": 11.35,
        "maid_data_points": 69
      },
      {
        "hotel_key": "daiichi_ikebukuro",
        "name": "第一イン池袋",
        "avg_maids": 5.7,
        "avg_checkers": 3.6,
        "avg_total_staff": 9.2,
        "maid_checker_ratio": 1.6,
        "score": 9.47,
        "cleaning_issue_rate": 1.4,
        "claim_rate": 7.95,
        "maid_data_points": 48
      },
      {
        "hotel_key": "comfort_roppongi",
        "name": "コンフォートイン六本木",
        "avg_maids": 5.5,
        "avg_checkers": 1.0,
        "avg_total_staff": 6.5,
        "maid_checker_ratio": 5.5,
        "score": 8.24,
        "cleaning_issue_rate": 4.3,
        "claim_rate": 4.35,
        "maid_data_points": 44
      },
      {
        "hotel_key": "comfort_suites_tokyobay",
        "name": "コンフォートスイーツ東京ベイ",
        "avg_maids": 23.5,
        "avg_checkers": 5.9,
        "avg_total_staff": 29.4,
        "maid_checker_ratio": 4.0,
        "score": 9.05,
        "cleaning_issue_rate": 0.0,
        "claim_rate": 8.42,
        "maid_data_points": 72
      },
      {
        "hotel_key": "comfort_era_higashikanda",
        "name": "コンフォートホテルERA東神田",
        "avg_maids": 8.1,
        "avg_checkers": null,
        "avg_total_staff": null,
        "maid_checker_ratio": null,
        "score": 8.78,
        "cleaning_issue_rate": 0.0,
        "claim_rate": 4.55,
        "maid_data_points": 59
      },
      {
        "hotel_key": "comfort_narita",
        "name": "コンフォートホテル成田",
        "avg_maids": 7.7,
        "avg_checkers": 1.0,
        "avg_total_staff": 8.7,
        "maid_checker_ratio": 7.7,
        "score": 8.56,
        "cleaning_issue_rate": 2.7,
        "claim_rate": 0,
        "maid_data_points": 21
      },
      {
        "hotel_key": "comfort_yokohama",
        "name": "コンフォートホテル横浜関内",
        "avg_maids": 10.7,
        "avg_checkers": 1.0,
        "avg_total_staff": 11.7,
        "maid_checker_ratio": 10.7,
        "score": 7.57,
        "cleaning_issue_rate": 8.4,
        "claim_rate": 5.39,
        "maid_data_points": 42
      },
      {
        "hotel_key": "apa_sagamihara",
        "name": "アパホテル相模原橋本駅東",
        "avg_maids": 7.6,
        "avg_checkers": 33.0,
        "avg_total_staff": 40.6,
        "maid_checker_ratio": 0.2,
        "score": 8.0,
        "cleaning_issue_rate": 3.3,
        "claim_rate": 6.21,
        "maid_data_points": 59
      },
      {
        "hotel_key": "apa_kamata",
        "name": "アパホテル蒲田駅東",
        "avg_maids": 12.9,
        "avg_checkers": 1.0,
        "avg_total_staff": 13.9,
        "maid_checker_ratio": 12.9,
        "score": 7.5,
        "cleaning_issue_rate": 10.7,
        "claim_rate": 8.39,
        "maid_data_points": 69
      },
      {
        "hotel_key": "court_shinyokohama",
        "name": "コートホテル新横浜",
        "avg_maids": 8.0,
        "avg_checkers": 2.6,
        "avg_total_staff": 10.6,
        "maid_checker_ratio": 3.1,
        "score": 7.12,
        "cleaning_issue_rate": 8.5,
        "claim_rate": 1.46,
        "maid_data_points": 47
      },
      {
        "hotel_key": "comment_yokohama",
        "name": "ホテルコメント横浜関内",
        "avg_maids": 9.4,
        "avg_checkers": 2.1,
        "avg_total_staff": 11.5,
        "maid_checker_ratio": 4.4,
        "score": 8.82,
        "cleaning_issue_rate": 4.6,
        "claim_rate": 7.3,
        "maid_data_points": 70
      },
      {
        "hotel_key": "henn_na_haneda",
        "name": "変なホテル東京羽田",
        "avg_maids": 12.1,
        "avg_checkers": 3.2,
        "avg_total_staff": 15.4,
        "maid_checker_ratio": 3.7,
        "score": 8.35,
        "cleaning_issue_rate": 1.2,
        "claim_rate": 6.59,
        "maid_data_points": 58
      },
      {
        "hotel_key": "kawasaki_nikko",
        "name": "川崎日航ホテル",
        "avg_maids": 6.6,
        "avg_checkers": 3.3,
        "avg_total_staff": 9.9,
        "maid_checker_ratio": 2.0,
        "score": 8.66,
        "cleaning_issue_rate": 1.4,
        "claim_rate": 17.42,
        "maid_data_points": 67
      },
      {
        "hotel_key": "comfort_hakata",
        "name": "コンフォートホテル博多",
        "avg_maids": 17.1,
        "avg_checkers": 5.2,
        "avg_total_staff": 22.4,
        "maid_checker_ratio": 3.3,
        "score": 7.83,
        "cleaning_issue_rate": 11.4,
        "claim_rate": 9.85,
        "maid_data_points": 57
      }
    ],
    "total_hotels_analyzed": 19
  },
  "hotel_summary": [
    {
      "hotel_key": "daiichi_ikebukuro",
      "name": "第一イン池袋",
      "days": 89,
      "avg_maids": 5.7,
      "avg_checkers": 3.6,
      "maid_checker_ratio": 1.6,
      "avg_completion_time": 15.14,
      "time_std": 0.2,
      "avg_rooms_per_maid": null,
      "score": 9.47,
      "claim_rate": 7.95,
      "maid_data_points": 48,
      "time_data_points": 11
    },
    {
      "hotel_key": "keisei_richmond",
      "name": "京成リッチモンドホテル東京錦糸町",
      "days": 89,
      "avg_maids": 8.3,
      "avg_checkers": 2.7,
      "maid_checker_ratio": 3.0,
      "avg_completion_time": 15.93,
      "time_std": 0.62,
      "avg_rooms_per_maid": 15.2,
      "score": 9.24,
      "claim_rate": 11.35,
      "maid_data_points": 69,
      "time_data_points": 56
    },
    {
      "hotel_key": "comfort_suites_tokyobay",
      "name": "コンフォートスイーツ東京ベイ",
      "days": 89,
      "avg_maids": 23.5,
      "avg_checkers": 5.9,
      "maid_checker_ratio": 4.0,
      "avg_completion_time": 15.46,
      "time_std": 0.51,
      "avg_rooms_per_maid": 11.4,
      "score": 9.05,
      "claim_rate": 8.42,
      "maid_data_points": 72,
      "time_data_points": 71
    },
    {
      "hotel_key": "keyakigate",
      "name": "ホテルケヤキゲート東京府中",
      "days": 89,
      "avg_maids": 10.3,
      "avg_checkers": 1.5,
      "maid_checker_ratio": 7.1,
      "avg_completion_time": 33.93,
      "time_std": 163.28,
      "avg_rooms_per_maid": 13.8,
      "score": 8.95,
      "claim_rate": 3.83,
      "maid_data_points": 72,
      "time_data_points": 71
    },
    {
      "hotel_key": "comment_yokohama",
      "name": "ホテルコメント横浜関内",
      "days": 89,
      "avg_maids": 9.4,
      "avg_checkers": 2.1,
      "maid_checker_ratio": 4.4,
      "avg_completion_time": 15.01,
      "time_std": 0.24,
      "avg_rooms_per_maid": 10.1,
      "score": 8.82,
      "claim_rate": 7.3,
      "maid_data_points": 70,
      "time_data_points": 69
    },
    {
      "hotel_key": "comfort_era_higashikanda",
      "name": "コンフォートホテルERA東神田",
      "days": 89,
      "avg_maids": 8.1,
      "avg_checkers": null,
      "maid_checker_ratio": null,
      "avg_completion_time": 15.25,
      "time_std": 0.6,
      "avg_rooms_per_maid": 19.0,
      "score": 8.78,
      "claim_rate": 4.55,
      "maid_data_points": 59,
      "time_data_points": 43
    },
    {
      "hotel_key": "kawasaki_nikko",
      "name": "川崎日航ホテル",
      "days": 89,
      "avg_maids": 6.6,
      "avg_checkers": 3.3,
      "maid_checker_ratio": 2.0,
      "avg_completion_time": 61.63,
      "time_std": 261.77,
      "avg_rooms_per_maid": 22.0,
      "score": 8.66,
      "claim_rate": 17.42,
      "maid_data_points": 67,
      "time_data_points": 68
    },
    {
      "hotel_key": "daiwa_osaki",
      "name": "ダイワロイネットホテル東京大崎",
      "days": 89,
      "avg_maids": 8.6,
      "avg_checkers": 2.6,
      "maid_checker_ratio": 3.3,
      "avg_completion_time": 14.6,
      "time_std": 0.37,
      "avg_rooms_per_maid": 20.0,
      "score": 8.59,
      "claim_rate": 11.83,
      "maid_data_points": 59,
      "time_data_points": 58
    },
    {
      "hotel_key": "comfort_narita",
      "name": "コンフォートホテル成田",
      "days": 89,
      "avg_maids": 7.7,
      "avg_checkers": 1.0,
      "maid_checker_ratio": 7.7,
      "avg_completion_time": 16.26,
      "time_std": 0.51,
      "avg_rooms_per_maid": 15.1,
      "score": 8.56,
      "claim_rate": 0,
      "maid_data_points": 21,
      "time_data_points": 18
    },
    {
      "hotel_key": "richmond_mejiro",
      "name": "リッチモンドホテル東京目白",
      "days": 89,
      "avg_maids": 6.0,
      "avg_checkers": 3.0,
      "maid_checker_ratio": 2.0,
      "avg_completion_time": 15.48,
      "time_std": 0.18,
      "avg_rooms_per_maid": 23.9,
      "score": 8.49,
      "claim_rate": 0,
      "maid_data_points": 57,
      "time_data_points": 57
    },
    {
      "hotel_key": "hearton",
      "name": "ハートンホテル東品川",
      "days": 89,
      "avg_maids": 12.3,
      "avg_checkers": 1.5,
      "maid_checker_ratio": 8.1,
      "avg_completion_time": 15.83,
      "time_std": 0.39,
      "avg_rooms_per_maid": null,
      "score": 8.43,
      "claim_rate": 7.27,
      "maid_data_points": 72,
      "time_data_points": 70
    },
    {
      "hotel_key": "henn_na_haneda",
      "name": "変なホテル東京羽田",
      "days": 89,
      "avg_maids": 12.1,
      "avg_checkers": 3.2,
      "maid_checker_ratio": 3.7,
      "avg_completion_time": 15.11,
      "time_std": 0.2,
      "avg_rooms_per_maid": 11.9,
      "score": 8.35,
      "claim_rate": 6.59,
      "maid_data_points": 58,
      "time_data_points": 54
    },
    {
      "hotel_key": "comfort_roppongi",
      "name": "コンフォートイン六本木",
      "days": 89,
      "avg_maids": 5.5,
      "avg_checkers": 1.0,
      "maid_checker_ratio": 5.5,
      "avg_completion_time": 1225.96,
      "time_std": 575.96,
      "avg_rooms_per_maid": 17.6,
      "score": 8.24,
      "claim_rate": 4.35,
      "maid_data_points": 44,
      "time_data_points": 38
    },
    {
      "hotel_key": "apa_sagamihara",
      "name": "アパホテル相模原橋本駅東",
      "days": 89,
      "avg_maids": 7.6,
      "avg_checkers": 33.0,
      "maid_checker_ratio": 0.2,
      "avg_completion_time": 15.32,
      "time_std": 0.5,
      "avg_rooms_per_maid": 14.2,
      "score": 8.0,
      "claim_rate": 6.21,
      "maid_data_points": 59,
      "time_data_points": 55
    },
    {
      "hotel_key": "comfort_hakata",
      "name": "コンフォートホテル博多",
      "days": 89,
      "avg_maids": 17.1,
      "avg_checkers": 5.2,
      "maid_checker_ratio": 3.3,
      "avg_completion_time": 15.87,
      "time_std": 0.7,
      "avg_rooms_per_maid": 13.0,
      "score": 7.83,
      "claim_rate": 9.85,
      "maid_data_points": 57,
      "time_data_points": 62
    },
    {
      "hotel_key": "comfort_yokohama",
      "name": "コンフォートホテル横浜関内",
      "days": 89,
      "avg_maids": 10.7,
      "avg_checkers": 1.0,
      "maid_checker_ratio": 10.7,
      "avg_completion_time": 15.22,
      "time_std": 0.53,
      "avg_rooms_per_maid": 16.8,
      "score": 7.57,
      "claim_rate": 5.39,
      "maid_data_points": 42,
      "time_data_points": 54
    },
    {
      "hotel_key": "apa_kamata",
      "name": "アパホテル蒲田駅東",
      "days": 89,
      "avg_maids": 12.9,
      "avg_checkers": 1.0,
      "maid_checker_ratio": 12.9,
      "avg_completion_time": 15.02,
      "time_std": 0.27,
      "avg_rooms_per_maid": 18.1,
      "score": 7.5,
      "claim_rate": 8.39,
      "maid_data_points": 69,
      "time_data_points": 67
    },
    {
      "hotel_key": "court_shinyokohama",
      "name": "コートホテル新横浜",
      "days": 59,
      "avg_maids": 8.0,
      "avg_checkers": 2.6,
      "maid_checker_ratio": 3.1,
      "avg_completion_time": 14.86,
      "time_std": 0.23,
      "avg_rooms_per_maid": 15.4,
      "score": 7.12,
      "claim_rate": 1.46,
      "maid_data_points": 47,
      "time_data_points": 47
    },
    {
      "hotel_key": "chisan",
      "name": "チサンホテル浜松町",
      "days": 89,
      "avg_maids": 9.2,
      "avg_checkers": null,
      "maid_checker_ratio": null,
      "avg_completion_time": 14.54,
      "time_std": 0.27,
      "avg_rooms_per_maid": null,
      "score": 6.52,
      "claim_rate": 0.53,
      "maid_data_points": 44,
      "time_data_points": 20
    }
  ],
  "recommendations": [
    {
      "title": "メイド・チェッカー比率の最適化",
      "rationale": "上位5ホテルの平均メイド:チェッカー比率は4.0:1、下位5ホテルは7.5:1。チェッカー配置の適正化がスコア向上に寄与する可能性。",
      "actions": [
        "メイド3〜5名に対しチェッカー1名の配置基準を設定",
        "高稼働日（150室超）は追加チェッカーの配置を検討",
        "チェッカー不在ホテルへの配置導入"
      ],
      "priority": "高"
    },
    {
      "title": "チェッカー配置とスコアの連動強化",
      "rationale": "チェッカー数とスコアの相関r=-0.1087。チェッカーによる品質検査がスコア改善の鍵。",
      "actions": [
        "チェッカー配置率100%を目標に採用・配置計画を策定",
        "チェッカー研修プログラムの統一と強化",
        "チェッカー不在時の代替チェック体制の確立"
      ],
      "priority": "最優先"
    },
    {
      "title": "データ入力の標準化と充実",
      "rationale": "日報のメイド数・チェッカー数の入力率がホテルにより大きく異なる。正確な分析のためにデータ品質向上が必要。",
      "actions": [
        "日報必須入力項目の明確化（メイド数・チェッカー数・完了時間）",
        "翌日稼働数の数値入力フォーマット統一",
        "月次での入力率チェックと改善フィードバック"
      ],
      "priority": "中"
    }
  ]
}